demo_fastapi/__init__.py
demo_fastapi/app.py
demo_fastapi/logging/__init__.py
demo_fastapi/logging/handlers.py
demo_fastapi/logging/settings.py
demo_fastapi/logging/setup.py
demo_fastapi/routes.py
demo_fastapi/tracing/__init__.py
demo_fastapi/tracing/middleware.py
demo_fastapi/tracing/settings.py
demo_fastapi/tracing/setup.py
demo_fastapi-0.5.0.dist-info/WHEEL
demo_fastapi-0.5.0.dist-info/METADATA
demo_fastapi-0.5.0.dist-info/RECORD
