Metadata-Version: 2.1
Name: demo-fastapi
Version: 0.5.0
Summary: Demonstration Rest API built using fastapi
Author: Guillaume Charbonnier
Author-email: guillaume.charbonnier@capgemini.com
Requires-Python: >=3.7,<4.0
Classifier: Programming Language :: Python :: 3
Classifier: Programming Language :: Python :: 3.7
Classifier: Programming Language :: Python :: 3.8
Classifier: Programming Language :: Python :: 3.9
Requires-Dist: fastapi (>=0.61.1,<0.62.0)
Requires-Dist: jaeger-client (>=4.3.0,<5.0.0)
Requires-Dist: loguru (>=0.5.3,<0.6.0)
Requires-Dist: opentracing (>=2.3.0,<3.0.0)
Requires-Dist: typer (>=0.3.2,<0.4.0)
Requires-Dist: uvicorn (>=0.12.1,<0.13.0)
